pepsift/__init__.py
pepsift/natural-aa.json
pepsift/pepsift.py
pepsift/utils.py
pepsift-0.0.2.post1.dist-info/LICENSE
pepsift-0.0.2.post1.dist-info/METADATA
pepsift-0.0.2.post1.dist-info/WHEEL
pepsift-0.0.2.post1.dist-info/top_level.txt
pepsift-0.0.2.post1.dist-info/RECORD
